paymium/__init__.py
paymium/api.py
paymium/base_bot.py
paymium/constants.py
paymium/controller.py
paymium/helper.py
paymium-1.0.dist-info/LICENSE
paymium-1.0.dist-info/METADATA
paymium-1.0.dist-info/WHEEL
paymium-1.0.dist-info/top_level.txt
paymium-1.0.dist-info/RECORD
